aii/__init__.py
aii/__main__.py
aii/main.py
aii/py.typed
aii/agents/__init__.py
aii/agents/shell_agent.py
aii/auth/__init__.py
aii/auth/browser_extractor.py
aii/auth/claude_oauth.py
aii/auth/extract_token.py
aii/auth/oauth_client.py
aii/auth/simple_extractor.py
aii/auth/subscription_client.py
aii/auth/test_console_script.js
aii/cli/__init__.py
aii/cli/aii_server_manager.py
aii/cli/client.py
aii/cli/command_parser.py
aii/cli/command_router.py
aii/cli/completion.py
aii/cli/confirmation.py
aii/cli/debug.py
aii/cli/input_processor.py
aii/cli/interactive_websocket.py
aii/cli/mcp_executor.py
aii/cli/mcp_streaming_adapter.py
aii/cli/output_formatter.py
aii/cli/response_streaming_formatter.py
aii/cli/server_manager.py
aii/cli/spinner.py
aii/cli/status_display.py
aii/cli/streaming_formatter.py
aii/cli/websocket_client.py
aii/cli/completion/__init__.py
aii/cli/completion/generator.py
aii/cli/completion/installer.py
aii/cli/handlers/__init__.py
aii/cli/handlers/config_handler.py
aii/cli/handlers/mcp_handler.py
aii/cli/handlers/other_handlers.py
aii/cli/handlers/prompt_create.py
aii/cli/handlers/prompt_handler.py
aii/cli/handlers/serve_handler.py
aii/cli/setup/__init__.py
aii/cli/setup/wizard.py
aii/cli/setup/steps/__init__.py
aii/cli/setup/steps/api_key_acquisition.py
aii/cli/setup/steps/base.py
aii/cli/setup/steps/model_selection.py
aii/cli/setup/steps/persistence.py
aii/cli/setup/steps/provider_selection.py
aii/cli/setup/steps/validation.py
aii/cli/setup/steps/web_search_setup.py
aii/cli/setup/ui/__init__.py
aii/cli/setup/ui/browser.py
aii/config/__init__.py
aii/config/llm-models.catalog.json
aii/config/manager.py
aii/config/output_config.py
aii/core/__init__.py
aii/core/prompt_engine.py
aii/data/__init__.py
aii/data/analytics/__init__.py
aii/data/analytics/cost_analyzer.py
aii/data/analytics/model_performance_analyzer.py
aii/data/analytics/models.py
aii/data/integrations/__init__.py
aii/data/integrations/mcp_client.py.deprecated
aii/data/integrations/mcp_health_monitor.py
aiiware_cli-0.12.1.dist-info/METADATA
aiiware_cli-0.12.1.dist-info/WHEEL
aiiware_cli-0.12.1.dist-info/entry_points.txt
aiiware_cli-0.12.1.dist-info/RECORD
