Metadata-Version: 2.4
Name: aiiware-cli
Version: 0.12.1
Summary: AI-powered terminal assistant with HTTP/WebSocket API: Natural language commands for git commits, code generation, translation, content writing, shell automation, and analysis. Choose your AI model per request (Claude, GPT-4, Gemini, Moonshot Kimi, DeepSeek). Includes model intelligence & analytics, cost optimization, 25+ content prompts, MCP server management, and IDE integrations (VSCode, Chrome extension).
Project-URL: Homepage, https://aiiware.com
Project-URL: Twitter, https://x.com/aii_dev
Project-URL: PyPI, https://pypi.org/project/aiiware-cli/
Author-email: Aii Dev <aii-dev@aiiware.com>
Maintainer-email: aii Dev <aii-dev@aiiware.com>
License: Apache-2.0
Keywords: ai,ai-api,ai-assistant,ai-cli,ai-code-review,ai-commands,ai-git-commit,ai-translation,ai-writing,api,automation,chatgpt-cli,chrome-extension,claude,claude-alternative,cli,code-analysis,code-assistant,code-explainer,code-generation,coding-assistant,command-line,commit-message-generator,content-generation,conversational-ai,copilot-alternative,cross-platform,deepseek,developer-tools,devtools,gemini,git-assistant,git-commit,gpt,gpt-4,http-api,ide-integration,kimi,llm,llm-api,llm-cli,mcp,mo
Classifier: Development Status :: 4 - Beta
Classifier: Environment :: Console
Classifier: Intended Audience :: Developers
Classifier: Intended Audience :: Information Technology
Classifier: Intended Audience :: Science/Research
Classifier: Intended Audience :: System Administrators
Classifier: License :: OSI Approved :: Apache Software License
Classifier: Natural Language :: English
Classifier: Operating System :: MacOS
Classifier: Operating System :: Microsoft :: Windows
Classifier: Operating System :: OS Independent
Classifier: Operating System :: POSIX
Classifier: Operating System :: Unix
Classifier: Programming Language :: Python :: 3
Classifier: Programming Language :: Python :: 3 :: Only
Classifier: Programming Language :: Python :: 3.10
Classifier: Programming Language :: Python :: 3.11
Classifier: Programming Language :: Python :: 3.12
Classifier: Programming Language :: Python :: Implementation :: CPython
Classifier: Topic :: Software Development
Classifier: Topic :: Software Development :: Code Generators
Classifier: Topic :: Software Development :: Libraries :: Python Modules
Classifier: Topic :: Software Development :: User Interfaces
Classifier: Topic :: Software Development :: Version Control :: Git
Classifier: Topic :: System :: Shells
Classifier: Topic :: System :: System Shells
Classifier: Topic :: Text Processing
Classifier: Topic :: Text Processing :: Linguistic
Classifier: Topic :: Utilities
Classifier: Typing :: Typed
Requires-Python: >=3.10
Requires-Dist: aiohttp>=3.9.0
Requires-Dist: aiosqlite>=0.19.0
Requires-Dist: click>=8.1.0
Requires-Dist: duckduckgo-search>=7.0.0
Requires-Dist: fastapi>=0.115.0
Requires-Dist: google-genai>=1.0.0
Requires-Dist: google-generativeai>=0.8.5
Requires-Dist: httpx>=0.28.0
Requires-Dist: importlib-metadata>=1.0; python_version < '3.8'
Requires-Dist: keyring>=24.0.0
Requires-Dist: mcp[cli]==1.25.0
Requires-Dist: psutil>=7.1.0
Requires-Dist: pydantic-ai>=1.0.6
Requires-Dist: pydantic>=2.10.0
Requires-Dist: python-dotenv>=1.0.0
Requires-Dist: pyyaml>=6.0.1
Requires-Dist: rich>=13.0.0
Requires-Dist: setproctitle>=1.3.0
Requires-Dist: types-pyyaml>=6.0.12.20250915
Requires-Dist: typing-extensions>=4.0.0; python_version < '3.11'
Requires-Dist: uvicorn>=0.32.0
Provides-Extra: dev
Requires-Dist: black>=25.1.0; extra == 'dev'
Requires-Dist: isort>=5.13.2; extra == 'dev'
Requires-Dist: mypy>=1.10.0; extra == 'dev'
Requires-Dist: pytest-asyncio>=0.25.0; extra == 'dev'
Requires-Dist: pytest-cov>=5.0.0; extra == 'dev'
Requires-Dist: pytest>=8.4.2; extra == 'dev'
Requires-Dist: ruff>=0.6.0; extra == 'dev'
Requires-Dist: types-psutil>=5.9.5.20240502; extra == 'dev'
